<?xml version='1.0' encoding='UTF-8'?> <!DOCTYPE tv SYSTEM "xmltv.dtd">
<tv generator-info-name="www.matthuisman.nz">
<channel id="5e20b730f2f8d5003d739db7-66a1ae9e77649467da169f0e">
    <display-name>Say Yes to the Dress</display-name>
    <icon src="https://provider-static.plex.tv/epg/cms/production/9298385b-b248-4e3b-87ee-fba261db99f9/SYTTD_Logo_Dark_1500x1000.png" />
  </channel>
  
<programme channel="5e20b730f2f8d5003d739db7-66a1ae9e77649467da169f0e" start="20250706000501 +0000" stop="20250706003034 +0000">
    <title>Say Yes to the Dress: Bridesmaids</title>
    <sub-title>Nautical and Military Maids</sub-title>
    <episode-num system="onscreen">S02E10</episode-num>
    <desc>A military bride battles her maids over how sexy her dresses should be.</desc>
    <date>20110805</date>
    <icon src="https://metadata-static.plex.tv/3/gracenote/311f5ba75e4dbe70033333c15603afb6.jpg" />
  </programme>
  
<programme channel="5e20b730f2f8d5003d739db7-66a1ae9e77649467da169f0e" start="20250706003034 +0000" stop="20250706005607 +0000">
    <title>Say Yes to the Dress: Bridesmaids</title>
    <sub-title>Many Maids and Many Dresses</sub-title>
    <episode-num system="onscreen">S02E11</episode-num>
    <desc>Lori's team has their hands full finding multiple dresses for many maids.</desc>
    <date>20110812</date>
    <icon src="https://metadata-static.plex.tv/e/gracenote/eef42d478d387e2d3d6f5f6328b3568b.jpg" />
  </programme>
  
<programme channel="5e20b730f2f8d5003d739db7-66a1ae9e77649467da169f0e" start="20250706005607 +0000" stop="20250706012140 +0000">
    <title>Say Yes to the Dress: Bridesmaids</title>
    <sub-title>Mother Knows Bridesmaids</sub-title>
    <episode-num system="onscreen">S02E12</episode-num>
    <desc>The mothers of the brides are in control of the salon today.</desc>
    <date>20110819</date>
    <icon src="https://metadata-static.plex.tv/e/gracenote/ef62f51263f749e514d822cdb101abe9.jpg" />
  </programme>
  
<programme channel="5e20b730f2f8d5003d739db7-66a1ae9e77649467da169f0e" start="20250706012140 +0000" stop="20250706014712 +0000">
    <title>Say Yes to the Dress: Bridesmaids</title>
    <sub-title>Sweet Brides and Sour Sisters</sub-title>
    <episode-num system="onscreen">S02E13</episode-num>
    <desc>A country bride is so sweet that she can't control her spicy bridesmaids.</desc>
    <date>20110826</date>
    <icon src="https://metadata-static.plex.tv/d/gracenote/de42b0efa4265f28771da4954c8df411.jpg" />
  </programme>
  
<programme channel="5e20b730f2f8d5003d739db7-66a1ae9e77649467da169f0e" start="20250706014712 +0000" stop="20250706021246 +0000">
    <title>Say Yes to the Dress: Bridesmaids</title>
    <sub-title>Jump for Joy With Your Cousins</sub-title>
    <episode-num system="onscreen">S02E14</episode-num>
    <desc>These brides have serious family issues on their hands.</desc>
    <date>20110902</date>
    <icon src="https://metadata-static.plex.tv/4/gracenote/4b2b1f57d470f6f0e9eff0b1c1d71b22.jpg" />
  </programme>
  
<programme channel="5e20b730f2f8d5003d739db7-66a1ae9e77649467da169f0e" start="20250706021246 +0000" stop="20250706023619 +0000">
    <title>Say Yes to the Dress: Bridesmaids</title>
    <sub-title>Bridesmaids Are No Angels</sub-title>
    <episode-num system="onscreen">S02E15</episode-num>
    <desc>A bridesmaid named Angel turns out to be anything but as she takes control.</desc>
    <date>20110909</date>
    <icon src="https://metadata-static.plex.tv/e/gracenote/eead9968c5a196975e09d7ff83aced23.jpg" />
  </programme>
  
<programme channel="5e20b730f2f8d5003d739db7-66a1ae9e77649467da169f0e" start="20250706023619 +0000" stop="20250706030151 +0000">
    <title>Say Yes to the Dress: Bridesmaids</title>
    <sub-title>Sorority and Sassy Sisters</sub-title>
    <episode-num system="onscreen">S02E16</episode-num>
    <desc>A bride's sassy sorority sisters gang up on her childhood friend.</desc>
    <date>20110916</date>
    <icon src="https://metadata-static.plex.tv/a/gracenote/a7b44d07eaee52be02232e906b33955d.jpg" />
  </programme>
  
<programme channel="5e20b730f2f8d5003d739db7-66a1ae9e77649467da169f0e" start="20250706030151 +0000" stop="20250706032725 +0000">
    <title>Say Yes to the Dress: Bridesmaids</title>
    <sub-title>Father Doesn't Know Best</sub-title>
    <episode-num system="onscreen">S02E17</episode-num>
    <desc>A bride's father takes over her shopping trip and vetoes dress after dress.</desc>
    <date>20110923</date>
    <icon src="https://metadata-static.plex.tv/6/gracenote/61ad92f6f15ec221c8886471155dc894.jpg" />
  </programme>
  
<programme channel="5e20b730f2f8d5003d739db7-66a1ae9e77649467da169f0e" start="20250706032725 +0000" stop="20250706035057 +0000">
    <title>Say Yes to the Dress: Bridesmaids</title>
    <sub-title>Say Yes to the Short Dress</sub-title>
    <episode-num system="onscreen">S02E18</episode-num>
    <desc>A bride battles her "Honorary Brides Man" for control of her dress choice.</desc>
    <date>20110930</date>
    <icon src="https://metadata-static.plex.tv/a/gracenote/a9ee36d34f7e2d100184792e4167d652.jpg" />
  </programme>
  
<programme channel="5e20b730f2f8d5003d739db7-66a1ae9e77649467da169f0e" start="20250706035057 +0000" stop="20250706041600 +0000">
    <title>Say Yes to the Dress: Bridesmaids</title>
    <sub-title>Trouble with the Twins</sub-title>
    <episode-num system="onscreen">S03E01</episode-num>
    <desc>Family drama heats up as a bride and her twin go against an older sister.</desc>
    <date>20120106</date>
    <icon src="https://metadata-static.plex.tv/6/gracenote/6532bc8cade78fe48a6e4656e5d950a1.jpg" />
  </programme>
  
<programme channel="5e20b730f2f8d5003d739db7-66a1ae9e77649467da169f0e" start="20250706041600 +0000" stop="20250706044103 +0000">
    <title>Say Yes to the Dress: Bridesmaids</title>
    <sub-title>22 Brawling Bridesmaids</sub-title>
    <episode-num system="onscreen">S03E02</episode-num>
    <desc>A bride has a record-breaking bridal party with 22 bridesmaids.</desc>
    <date>20120106</date>
    <icon src="https://metadata-static.plex.tv/3/gracenote/3c608e4e5c6dd75990952097c7199cd5.jpg" />
  </programme>
  
<programme channel="5e20b730f2f8d5003d739db7-66a1ae9e77649467da169f0e" start="20250706044103 +0000" stop="20250706050405 +0000">
    <title>Say Yes to the Dress: Bridesmaids</title>
    <sub-title>Pink, Pink, Pink!</sub-title>
    <episode-num system="onscreen">S03E03</episode-num>
    <desc>A bride battles her mom, who wants her maids to look like pink ballerinas.</desc>
    <date>20120113</date>
    <icon src="https://metadata-static.plex.tv/1/gracenote/11412bc53d0a10acba94897aa8e2e8d2.jpg" />
  </programme>
  
<programme channel="5e20b730f2f8d5003d739db7-66a1ae9e77649467da169f0e" start="20250706050405 +0000" stop="20250706052909 +0000">
    <title>Say Yes to the Dress: Bridesmaids</title>
    <sub-title>Miss America's Maids</sub-title>
    <episode-num system="onscreen">S03E04</episode-num>
    <desc>The salon is buzzing with excitement for Miss America's 5-star wedding.</desc>
    <date>20120113</date>
    <icon src="https://metadata-static.plex.tv/8/gracenote/8beb43ec7c730a441e0b8d2eff02f442.jpg" />
  </programme>
  
<programme channel="5e20b730f2f8d5003d739db7-66a1ae9e77649467da169f0e" start="20250706052909 +0000" stop="20250706055211 +0000">
    <title>Say Yes to the Dress: Bridesmaids</title>
    <sub-title>Maids Gotta Go-Go</sub-title>
    <episode-num system="onscreen">S03E05</episode-num>
    <desc>A mother of the bride lashes out at a bridesmaid.</desc>
    <date>20120120</date>
    <icon src="https://metadata-static.plex.tv/8/gracenote/8ec4398bb42aa6141c4079018aedab4e.jpg" />
  </programme>
  
<programme channel="5e20b730f2f8d5003d739db7-66a1ae9e77649467da169f0e" start="20250706055211 +0000" stop="20250706061514 +0000">
    <title>Say Yes to the Dress: Bridesmaids</title>
    <sub-title>Black Sheep</sub-title>
    <episode-num system="onscreen">S03E06</episode-num>
    <desc>A baby of the family must find the courage to stand up to her sisters.</desc>
    <date>20120120</date>
    <icon src="https://metadata-static.plex.tv/3/gracenote/3e81ed5907c5b7326b4bc3efbb939cc8.jpg" />
  </programme>
  
<programme channel="5e20b730f2f8d5003d739db7-66a1ae9e77649467da169f0e" start="20250706061514 +0000" stop="20250706064016 +0000">
    <title>Say Yes to the Dress: Bridesmaids</title>
    <sub-title>Political Parties</sub-title>
    <episode-num system="onscreen">S03E07</episode-num>
    <desc>Two maids campaign for the ultimate bridal title of Maid of Honor.</desc>
    <date>20120127</date>
    <icon src="https://metadata-static.plex.tv/6/gracenote/6179c3d0d3c727f46b373af1483f50ed.jpg" />
  </programme>
  
<programme channel="5e20b730f2f8d5003d739db7-66a1ae9e77649467da169f0e" start="20250706064016 +0000" stop="20250706070319 +0000">
    <title>Say Yes to the Dress: Bridesmaids</title>
    <sub-title>Orange Appeal</sub-title>
    <episode-num system="onscreen">S03E08</episode-num>
    <desc>A bride struggles when her bossy older sister teams up with her fiance.</desc>
    <date>20120127</date>
    <icon src="https://metadata-static.plex.tv/a/gracenote/a54d339eb8452af4742549e4d0a6c1af.jpg" />
  </programme>
  
<programme channel="5e20b730f2f8d5003d739db7-66a1ae9e77649467da169f0e" start="20250706070319 +0000" stop="20250706072822 +0000">
    <title>Say Yes to the Dress: Bridesmaids</title>
    <sub-title>Tiaras and Tribulations</sub-title>
    <episode-num system="onscreen">S03E09</episode-num>
    <desc>Lori returns to the shop and helps two sisters battling over a tiara.</desc>
    <date>20120203</date>
    <icon src="https://metadata-static.plex.tv/8/gracenote/886d3ed93b411b67dc66288e14ac33e6.jpg" />
  </programme>
  
<programme channel="5e20b730f2f8d5003d739db7-66a1ae9e77649467da169f0e" start="20250706072822 +0000" stop="20250706075324 +0000">
    <title>Say Yes to the Dress: Bridesmaids</title>
    <sub-title>Thou Shall Not Wear Strapless</sub-title>
    <episode-num system="onscreen">S03E10</episode-num>
    <desc>A bride's best friend can also be her worst enemy.</desc>
    <date>20121002</date>
    <icon src="https://metadata-static.plex.tv/4/gracenote/42d31976ba07e98666b51a5b83c94a60.jpg" />
  </programme>
  
<programme channel="5e20b730f2f8d5003d739db7-66a1ae9e77649467da169f0e" start="20250706075324 +0000" stop="20250706081627 +0000">
    <title>Say Yes to the Dress: Bridesmaids</title>
    <sub-title>No Passion for Fashion</sub-title>
    <episode-num system="onscreen">S03E11</episode-num>
    <desc>A bride gets bullied by her groom's sexy sister.</desc>
    <date>20120217</date>
    <icon src="https://metadata-static.plex.tv/0/gracenote/09d7ec64fda2fbf4988ee95f11c44c46.jpg" />
  </programme>
  
<programme channel="5e20b730f2f8d5003d739db7-66a1ae9e77649467da169f0e" start="20250706081627 +0000" stop="20250706084129 +0000">
    <title>Say Yes to the Dress: Bridesmaids</title>
    <sub-title>Mama-in-Law Knows Best</sub-title>
    <episode-num system="onscreen">S03E12</episode-num>
    <desc>Brides battle a bossy mother-in-law, older sister and wedding planner.</desc>
    <date>20120224</date>
    <icon src="https://metadata-static.plex.tv/0/gracenote/05308f8331fc2e2ac4c2b8a56b4996cc.jpg" />
  </programme>
  
<programme channel="5e20b730f2f8d5003d739db7-66a1ae9e77649467da169f0e" start="20250706084129 +0000" stop="20250706090632 +0000">
    <title>Say Yes to the Dress: Bridesmaids</title>
    <sub-title>Potty Party</sub-title>
    <episode-num system="onscreen">S03E13</episode-num>
    <desc>A bride fights with her mother and maid of honor over a slinky dress.</desc>
    <date>20120302</date>
    <icon src="https://metadata-static.plex.tv/e/gracenote/e8f6fa8072622e4f9411c391a2dc3380.jpg" />
  </programme>
  
<programme channel="5e20b730f2f8d5003d739db7-66a1ae9e77649467da169f0e" start="20250706090632 +0000" stop="20250706092935 +0000">
    <title>Say Yes to the Dress: Bridesmaids</title>
    <sub-title>In-Law and Order</sub-title>
    <episode-num system="onscreen">S03E14</episode-num>
    <desc>Bride Courtney learns very quickly that family isn't always on your side.</desc>
    <date>20120309</date>
    <icon src="https://metadata-static.plex.tv/2/gracenote/2c0e5efc4d4c43662b394a03c26ea04d.jpg" />
  </programme>
  
<programme channel="5e20b730f2f8d5003d739db7-66a1ae9e77649467da169f0e" start="20250706092935 +0000" stop="20250706095437 +0000">
    <title>Say Yes to the Dress: Bridesmaids</title>
    <sub-title>Sisters and Frothers</sub-title>
    <episode-num system="onscreen">S03E15</episode-num>
    <desc>A bride's bossy big sister is fighting her tooth and nail over a dress.</desc>
    <date>20120316</date>
    <icon src="https://metadata-static.plex.tv/4/gracenote/4260c11d32db075bb5e150995793d3ef.jpg" />
  </programme>
  
<programme channel="5e20b730f2f8d5003d739db7-66a1ae9e77649467da169f0e" start="20250706095437 +0000" stop="20250706101940 +0000">
    <title>Say Yes to the Dress: Bridesmaids</title>
    <sub-title>Size Matters...</sub-title>
    <episode-num system="onscreen">S03E16</episode-num>
    <desc>A husband-hunting bridesmaid wants to show off her body in a sexy dress.</desc>
    <date>20120323</date>
    <icon src="https://metadata-static.plex.tv/9/gracenote/945f9f5a41cf4370ff7e83457faaef58.jpg" />
  </programme>
  
<programme channel="5e20b730f2f8d5003d739db7-66a1ae9e77649467da169f0e" start="20250706101940 +0000" stop="20250706104243 +0000">
    <title>Say Yes to the Dress: Bridesmaids</title>
    <sub-title>Show Up and Shut Up</sub-title>
    <episode-num system="onscreen">S03E17</episode-num>
    <desc>When a bride has trouble deciding on a color, her bridesmaids get fed up.</desc>
    <date>20120330</date>
    <icon src="https://metadata-static.plex.tv/b/gracenote/b357103ab8f2d0d483f165394f6aa8f8.jpg" />
  </programme>
  
<programme channel="5e20b730f2f8d5003d739db7-66a1ae9e77649467da169f0e" start="20250706104243 +0000" stop="20250706110746 +0000">
    <title>Say Yes to the Dress: Bridesmaids</title>
    <sub-title>Daycare by Lori</sub-title>
    <episode-num system="onscreen">S03E18</episode-num>
    <desc>With pouting and tears at an all-time high, the salon feels like a daycare!</desc>
    <date>20120406</date>
    <icon src="https://metadata-static.plex.tv/b/gracenote/be4d7b592708e2a36264505b2f3a698e.jpg" />
  </programme>
  
<programme channel="5e20b730f2f8d5003d739db7-66a1ae9e77649467da169f0e" start="20250706110746 +0000" stop="20250706113248 +0000">
    <title>Say Yes to the Dress: Bridesmaids</title>
    <sub-title>Cold Feet and Hot Tempers</sub-title>
    <episode-num system="onscreen">S04E01</episode-num>
    <desc>Renee deals with her friend's jealousy after appointing her "man of honor."</desc>
    <date>20120824</date>
    <icon src="https://metadata-static.plex.tv/2/gracenote/279a0a13f6402a4d727835f1b6fdada3.jpg" />
  </programme>
  
<programme channel="5e20b730f2f8d5003d739db7-66a1ae9e77649467da169f0e" start="20250706113248 +0000" stop="20250706115736 +0000">
    <title>Say Yes to the Dress: Bridesmaids</title>
    <sub-title>Girl Power</sub-title>
    <episode-num system="onscreen">S04E02</episode-num>
    <desc>A bride brings her fiance as backup against her bullying sister.</desc>
    <date>20120824</date>
    <icon src="https://metadata-static.plex.tv/a/gracenote/aef77c796f9dc41678a55d5228371912.jpg" />
  </programme>
  
<programme channel="5e20b730f2f8d5003d739db7-66a1ae9e77649467da169f0e" start="20250706115736 +0000" stop="20250706122240 +0000">
    <title>Say Yes to the Dress: Bridesmaids</title>
    <sub-title>PhD in Persuasion</sub-title>
    <episode-num system="onscreen">S04E03</episode-num>
    <desc>A bride's sister uses her psychology background to manipulate the bride.</desc>
    <date>20120831</date>
    <icon src="https://metadata-static.plex.tv/1/gracenote/17056ffe313586d9ad50d4f18e32660e.jpg" />
  </programme>
  
<programme channel="5e20b730f2f8d5003d739db7-66a1ae9e77649467da169f0e" start="20250706122240 +0000" stop="20250706124542 +0000">
    <title>Say Yes to the Dress: Bridesmaids</title>
    <sub-title>Jarring Politics</sub-title>
    <episode-num system="onscreen">S04E04</episode-num>
    <desc>Esther's maid of honor has given herself veto power over all dresses.</desc>
    <date>20120831</date>
    <icon src="https://metadata-static.plex.tv/c/gracenote/c12c95ef74a5818883b14a90862d3a67.jpg" />
  </programme>
  
<programme channel="5e20b730f2f8d5003d739db7-66a1ae9e77649467da169f0e" start="20250706124542 +0000" stop="20250706131046 +0000">
    <title>Say Yes to the Dress: Bridesmaids</title>
    <sub-title>Pray for Peace</sub-title>
    <episode-num system="onscreen">S04E05</episode-num>
    <desc>When dress shopping gets difficult, a bride's mean-girl spirit comes out.</desc>
    <date>20120907</date>
    <icon src="https://metadata-static.plex.tv/8/gracenote/848c61d945a6762d5364f46a0d4afb07.jpg" />
  </programme>
  
<programme channel="5e20b730f2f8d5003d739db7-66a1ae9e77649467da169f0e" start="20250706131046 +0000" stop="20250706133348 +0000">
    <title>Say Yes to the Dress: Bridesmaids</title>
    <sub-title>Falling Apart at the Seams</sub-title>
    <episode-num system="onscreen">S04E06</episode-num>
    <desc>Two grooms have high hopes for their big day, but their visions clash.</desc>
    <date>20120907</date>
    <icon src="https://metadata-static.plex.tv/f/gracenote/f77bdb024dfdcc79ddea1effcdd38912.jpg" />
  </programme>
  
<programme channel="5e20b730f2f8d5003d739db7-66a1ae9e77649467da169f0e" start="20250706133348 +0000" stop="20250706135852 +0000">
    <title>Say Yes to the Dress: Bridesmaids</title>
    <sub-title>Mudslingin' Mamas</sub-title>
    <episode-num system="onscreen">S04E07</episode-num>
    <desc>A brash Southern mama's antics make the bridesmaids feel self-conscious.</desc>
    <date>20120914</date>
    <icon src="https://metadata-static.plex.tv/9/gracenote/914a39eec756b189f6f4f6e89c121ac7.jpg" />
  </programme>
  
<programme channel="5e20b730f2f8d5003d739db7-66a1ae9e77649467da169f0e" start="20250706135852 +0000" stop="20250706142355 +0000">
    <title>Say Yes to the Dress: Bridesmaids</title>
    <sub-title>Catfight on the Catwalk</sub-title>
    <episode-num system="onscreen">S04E08</episode-num>
    <desc>Bride Cassie's fighting maids threaten their relationship with the bride.</desc>
    <date>20120914</date>
    <icon src="https://metadata-static.plex.tv/4/gracenote/4c7746a8159de103acbb23c1b63a2f34.jpg" />
  </programme>
  
<programme channel="5e20b730f2f8d5003d739db7-66a1ae9e77649467da169f0e" start="20250706142355 +0000" stop="20250706144857 +0000">
    <title>Say Yes to the Dress: Bridesmaids</title>
    <sub-title>Singled Out</sub-title>
    <episode-num system="onscreen">S04E09</episode-num>
    <desc>A single mom's tight budget makes it challenging to find a dress.</desc>
    <date>20120921</date>
    <icon src="https://metadata-static.plex.tv/5/gracenote/5fe5136d9e56ae2f31a54236107eba41.jpg" />
  </programme>
  
<programme channel="5e20b730f2f8d5003d739db7-66a1ae9e77649467da169f0e" start="20250706144857 +0000" stop="20250706151401 +0000">
    <title>Say Yes to the Dress: Bridesmaids</title>
    <sub-title>Breaking the Rules</sub-title>
    <episode-num system="onscreen">S04E10</episode-num>
    <desc>A bride walks out after her party-girl sister advocates for short dresses.</desc>
    <date>20120921</date>
    <icon src="https://metadata-static.plex.tv/3/gracenote/3aeda3e8f44d50fd794c3a9df59f3e59.jpg" />
  </programme>
  
<programme channel="5e20b730f2f8d5003d739db7-66a1ae9e77649467da169f0e" start="20250706151401 +0000" stop="20250706153734 +0000">
    <title>Say Yes to the Dress</title>
    <sub-title>Changes and Challenges</sub-title>
    <episode-num system="onscreen">S03E01</episode-num>
    <desc>A bride wants a dress that will help her honor a recently deceased sibling.</desc>
    <date>20090306</date>
    <icon src="https://image.tmdb.org/t/p/original/jc0yHLjoMHMh3kRWFDQ4ssSdhpi.jpg" />
  </programme>
  
<programme channel="5e20b730f2f8d5003d739db7-66a1ae9e77649467da169f0e" start="20250706153734 +0000" stop="20250706160107 +0000">
    <title>Say Yes to the Dress</title>
    <sub-title>In My Opinion</sub-title>
    <episode-num system="onscreen">S03E02</episode-num>
    <desc>Everyone thinks they know best at the bridal salon -- especially the bride.</desc>
    <date>20090306</date>
    <icon src="https://image.tmdb.org/t/p/original/jCqmgoGAP8JOm27k4AG02HqhzHf.jpg" />
  </programme>
  
<programme channel="5e20b730f2f8d5003d739db7-66a1ae9e77649467da169f0e" start="20250706160107 +0000" stop="20250706162639 +0000">
    <title>Say Yes to the Dress</title>
    <sub-title>Once Upon a Dress</sub-title>
    <episode-num system="onscreen">S03E03</episode-num>
    <desc>Adriana is searching for the perfect dress for her "happily ever after."</desc>
    <date>20090313</date>
    <icon src="https://image.tmdb.org/t/p/original/9QzH73Fn0LI61tUsAhTuZPInoEu.jpg" />
  </programme>
  
<programme channel="5e20b730f2f8d5003d739db7-66a1ae9e77649467da169f0e" start="20250706162639 +0000" stop="20250706165213 +0000">
    <title>Say Yes to the Dress</title>
    <sub-title>Bridal Wave</sub-title>
    <episode-num system="onscreen">S03E04</episode-num>
    <desc>Bride Jessica brings scorecards to ensure an honest opinion of her gowns.</desc>
    <date>20090320</date>
    <icon src="https://image.tmdb.org/t/p/original/6a2tUXzyM2urXC0D62R7XO67cFf.jpg" />
  </programme>
  
<programme channel="5e20b730f2f8d5003d739db7-66a1ae9e77649467da169f0e" start="20250706165213 +0000" stop="20250706171545 +0000">
    <title>Say Yes to the Dress</title>
    <sub-title>Playing Dress Up</sub-title>
    <episode-num system="onscreen">S03E05</episode-num>
    <desc>There's something fishy about an appointment made by a bride's friends.</desc>
    <date>20090403</date>
    <icon src="https://image.tmdb.org/t/p/original/9VEXwkSwICPasnx4wjamew7uELg.jpg" />
  </programme>
  
<programme channel="5e20b730f2f8d5003d739db7-66a1ae9e77649467da169f0e" start="20250706171545 +0000" stop="20250706173918 +0000">
    <title>Say Yes to the Dress</title>
    <sub-title>The Dress Ties that Bind</sub-title>
    <episode-num system="onscreen">S03E06</episode-num>
    <desc>Religious differences cause a rift between a bride and her mother in law.</desc>
    <date>20090410</date>
    <icon src="https://image.tmdb.org/t/p/original/yq8S9keP00DpkbpW1BZQ9jgJDBt.jpg" />
  </programme>
  
<programme channel="5e20b730f2f8d5003d739db7-66a1ae9e77649467da169f0e" start="20250706173918 +0000" stop="20250706180452 +0000">
    <title>Say Yes to the Dress</title>
    <sub-title>Seeing Red</sub-title>
    <episode-num system="onscreen">S03E07</episode-num>
    <desc>Jasleen wants an elaborate dress in red for under $2,000.</desc>
    <date>20090417</date>
    <icon src="https://image.tmdb.org/t/p/original/xq2UruODNklFuW7E9ztri4CjhVr.jpg" />
  </programme>
  
<programme channel="5e20b730f2f8d5003d739db7-66a1ae9e77649467da169f0e" start="20250706180452 +0000" stop="20250706182826 +0000">
    <title>Say Yes to the Dress</title>
    <sub-title>Hot Dresses, Cold Feet</sub-title>
    <episode-num system="onscreen">S03E08</episode-num>
    <desc>Sacha refuses to settle for a dress within her budget.</desc>
    <date>20090424</date>
    <icon src="https://image.tmdb.org/t/p/original/rkicqtrFMsCwyI6XJoaj1TVCUR6.jpg" />
  </programme>
  
<programme channel="5e20b730f2f8d5003d739db7-66a1ae9e77649467da169f0e" start="20250706182826 +0000" stop="20250706185359 +0000">
    <title>Say Yes to the Dress</title>
    <sub-title>There's A First For Everything</sub-title>
    <episode-num system="onscreen">S03E09</episode-num>
    <desc>Jessica wants a fairy-themed wedding and a dress to go with fairy wings.</desc>
    <date>20090501</date>
    <icon src="https://image.tmdb.org/t/p/original/yNpBgl8wtVC7zkPTVbgyZV8CrrL.jpg" />
  </programme>
  
<programme channel="5e20b730f2f8d5003d739db7-66a1ae9e77649467da169f0e" start="20250706185359 +0000" stop="20250706191931 +0000">
    <title>Say Yes to the Dress</title>
    <sub-title>The Art of Negotiation</sub-title>
    <episode-num system="onscreen">S03E10</episode-num>
    <desc>Fofie finds her dream dress, but her father will not pay the asking price.</desc>
    <date>20090508</date>
    <icon src="https://image.tmdb.org/t/p/original/vxI5P1jdUvPtwBIXgF1ZTyUm8nZ.jpg" />
  </programme>
  
<programme channel="5e20b730f2f8d5003d739db7-66a1ae9e77649467da169f0e" start="20250706191931 +0000" stop="20250706194502 +0000">
    <title>Say Yes to the Dress</title>
    <sub-title>Getting in the Spirit</sub-title>
    <episode-num system="onscreen">S03E11</episode-num>
    <desc>A woman searches for a dress that fits her culture and her style.</desc>
    <date>20090515</date>
    <icon src="https://image.tmdb.org/t/p/original/hgrhtPGSLj9xyUXhjQOWgx8cX5Q.jpg" />
  </programme>
  
<programme channel="5e20b730f2f8d5003d739db7-66a1ae9e77649467da169f0e" start="20250706194502 +0000" stop="20250706200835 +0000">
    <title>Say Yes to the Dress</title>
    <sub-title>Second Time Around</sub-title>
    <episode-num system="onscreen">S03E12</episode-num>
    <desc>Carmel helps a bride who is having a military wedding after eloping.</desc>
    <date>20090605</date>
    <icon src="https://image.tmdb.org/t/p/original/9J3pPJRuF0t4jwgK6nnlvkJ7b8E.jpg" />
  </programme>
  
<programme channel="5e20b730f2f8d5003d739db7-66a1ae9e77649467da169f0e" start="20250706200835 +0000" stop="20250706203207 +0000">
    <title>Say Yes to the Dress</title>
    <sub-title>Clicking with Brides</sub-title>
    <episode-num system="onscreen">S03E13</episode-num>
    <desc>Leah's opinionated maid-of-honor is a challenge for consultant Dianne.</desc>
    <date>20090626</date>
    <icon src="https://image.tmdb.org/t/p/original/6Fok4bY0Wl0vBL1GhnlSAolH0Vs.jpg" />
  </programme>
  
<programme channel="5e20b730f2f8d5003d739db7-66a1ae9e77649467da169f0e" start="20250706203207 +0000" stop="20250706205741 +0000">
    <title>Say Yes to the Dress</title>
    <sub-title>Two For One</sub-title>
    <episode-num system="onscreen">S03E14</episode-num>
    <desc>Debbie and Carmel team up in order to sell dresses to sister brides.</desc>
    <date>20090710</date>
    <icon src="https://image.tmdb.org/t/p/original/l5iV5tVMGmgI66fVU7c223wsrxC.jpg" />
  </programme>
  
<programme channel="5e20b730f2f8d5003d739db7-66a1ae9e77649467da169f0e" start="20250706205741 +0000" stop="20250706212113 +0000">
    <title>Say Yes to the Dress</title>
    <sub-title>Missing Mom</sub-title>
    <episode-num system="onscreen">S03E15</episode-num>
    <desc>A bride who has lost her mother to cancer battles an opinionated aunt.</desc>
    <date>20090619</date>
    <icon src="https://image.tmdb.org/t/p/original/73ToZ1Y1hSlavQbGkYeZXqJtAZ9.jpg" />
  </programme>
  
<programme channel="5e20b730f2f8d5003d739db7-66a1ae9e77649467da169f0e" start="20250706212113 +0000" stop="20250706214647 +0000">
    <title>Say Yes to the Dress</title>
    <sub-title>Family Dynamics</sub-title>
    <episode-num system="onscreen">S03E16</episode-num>
    <desc>A bride and her mother don't know how to hold back their brutal opinions.</desc>
    <date>20090717</date>
    <icon src="https://image.tmdb.org/t/p/original/1QSIjD3m9Nin4OTjJp7LPwMJ6lS.jpg" />
  </programme>
  
<programme channel="5e20b730f2f8d5003d739db7-66a1ae9e77649467da169f0e" start="20250706214647 +0000" stop="20250706221221 +0000">
    <title>Say Yes to the Dress</title>
    <sub-title>Indecisive Brides</sub-title>
    <episode-num system="onscreen">S03E17</episode-num>
    <desc>An edgy bride returns to find a dress style that better suits her.</desc>
    <date>20090724</date>
    <icon src="https://image.tmdb.org/t/p/original/hXT86YQW6F58zDIqeMnS1li7sLX.jpg" />
  </programme>
  
<programme channel="5e20b730f2f8d5003d739db7-66a1ae9e77649467da169f0e" start="20250706221221 +0000" stop="20250706223754 +0000">
    <title>Say Yes to the Dress</title>
    <sub-title>Goals</sub-title>
    <episode-num system="onscreen">S03E18</episode-num>
    <desc>A consultant works with a bride who donated her kidney to her fiance.</desc>
    <date>20090731</date>
    <icon src="https://image.tmdb.org/t/p/original/8OKYuxbKOHCdZyDR2u36nFykLHA.jpg" />
  </programme>
  
<programme channel="5e20b730f2f8d5003d739db7-66a1ae9e77649467da169f0e" start="20250706223754 +0000" stop="20250706230326 +0000">
    <title>Say Yes to the Dress</title>
    <sub-title>Overbooked</sub-title>
    <episode-num system="onscreen">S04E01</episode-num>
    <desc>A former beauty queen wants a traditional dress and not a pageant gown.</desc>
    <date>20090911</date>
    <icon src="https://image.tmdb.org/t/p/original/4cdQgKtmOhstN3c3Qw27nAX8mM1.jpg" />
  </programme>
  
<programme channel="5e20b730f2f8d5003d739db7-66a1ae9e77649467da169f0e" start="20250706230326 +0000" stop="20250706232659 +0000">
    <title>Say Yes to the Dress</title>
    <sub-title>Practically Family</sub-title>
    <episode-num system="onscreen">S04E02</episode-num>
    <desc>Tiffany's mom balks when Tiffany wants a hot pink dress.</desc>
    <date>20090911</date>
    <icon src="https://image.tmdb.org/t/p/original/gA05tgeqcEoOphxbdtTWbMtUazD.jpg" />
  </programme>
  
<programme channel="5e20b730f2f8d5003d739db7-66a1ae9e77649467da169f0e" start="20250706232659 +0000" stop="20250706235232 +0000">
    <title>Say Yes to the Dress</title>
    <sub-title>Going the Extra Mile</sub-title>
    <episode-num system="onscreen">S04E03</episode-num>
    <desc>Debbie finds a dress for a bride who's getting married in just five weeks.</desc>
    <date>20090918</date>
    <icon src="https://image.tmdb.org/t/p/original/7Fb00aY1mYKQW0AIyoTV0RtApPS.jpg" />
  </programme>
  
<programme channel="5e20b730f2f8d5003d739db7-66a1ae9e77649467da169f0e" start="20250706235232 +0000" stop="20250707001806 +0000">
    <title>Say Yes to the Dress</title>
    <sub-title>Veterans vs. Rookies</sub-title>
    <episode-num system="onscreen">S04E04</episode-num>
    <desc>Rookie consultant Jessica joins the team, and Mirjana needs a dress NOW.</desc>
    <date>20090918</date>
    <icon src="https://image.tmdb.org/t/p/original/20IukiqzwtH0hOr0eqXnzKWZDdp.jpg" />
  </programme>
  
</tv>
